fsm-assignments/problem4_link/slave_fsm.v
`timescale 1ns/1ps

module slave_fsm(
  input  wire       clk,
  input  wire       rst,   // sync active-high reset
  input  wire       req,
  input  wire [7:0] data_in,
  output reg        ack,
  output reg [7:0]  last_byte
);

  reg [1:0] state;
  reg [1:0] ack_cnt;

  localparam S_WAIT_REQ  = 2'd0,
             S_HOLD_ACK  = 2'd1,
             S_DROP_ACK  = 2'd2;

  always @(posedge clk) begin
    if (rst) begin
      state     <= S_WAIT_REQ;
      ack       <= 0;
      ack_cnt   <= 0;
      last_byte <= 8'h00;
    end else begin
      case (state)
        S_WAIT_REQ: begin
          if (req) begin
            last_byte <= data_in;
            ack       <= 1;
            ack_cnt   <= 0;
            state     <= S_HOLD_ACK;
          end
        end

        S_HOLD_ACK: begin
          ack_cnt <= ack_cnt + 1;
          if (ack_cnt == 1) begin  // 2 cycles total
            state <= S_DROP_ACK;
          end
        end

        S_DROP_ACK: begin
          ack <= 0;
          if (!req) state <= S_WAIT_REQ;
        end
      endcase
    end
  end
endmodule

fsm-assignments/problem4_link/master_fsm.v
`timescale 1ns/1ps

module master_fsm(
  input  wire       clk,
  input  wire       rst,   // sync active-high reset
  input  wire       ack,
  output reg        req,
  output reg [7:0]  data,
  output reg        done
);

  reg [1:0] state;
  reg [1:0] byte_cnt;  // 4-byte burst
  reg [7:0] mem [0:3]; // data to send

  localparam S_IDLE       = 2'd0,
             S_WAIT_ACK   = 2'd1,
             S_WAIT_ACK0  = 2'd2,
             S_DONE       = 2'd3;

  always @(posedge clk) begin
    if (rst) begin
      state    <= S_IDLE;
      req      <= 0;
      done     <= 0;
      byte_cnt <= 0;
      // preload data bytes
      mem[0]   <= 8'hA0;
      mem[1]   <= 8'hA1;
      mem[2]   <= 8'hA2;
      mem[3]   <= 8'hA3;
    end else begin
      done <= 0; // default unless DONE state
      case (state)
        S_IDLE: begin
          req   <= 1;
          data  <= mem[byte_cnt];
          state <= S_WAIT_ACK;
        end

        S_WAIT_ACK: begin
          if (ack) begin
            req   <= 0;
            state <= S_WAIT_ACK0;
          end
        end

        S_WAIT_ACK0: begin
          if (!ack) begin
            byte_cnt <= byte_cnt + 1;
            if (byte_cnt == 2'd3) begin
              state <= S_DONE;
            end else begin
              req   <= 1;
              data  <= mem[byte_cnt+1];
              state <= S_WAIT_ACK;
            end
          end
        end

        S_DONE: begin
          done     <= 1;
          byte_cnt <= 0;
          state    <= S_IDLE;
        end
      endcase
    end
  end
endmodule

fsm-assignments/problem4_link/link_top.v
`timescale 1ns/1ps

module link_top(
  input  wire clk,
  input  wire rst,
  output wire done
);

  wire       req_sig, ack_sig;
  wire [7:0] data_sig;
  wire [7:0] last_byte_sig; // can probe for TB

  master_fsm u_master (
    .clk(clk),
    .rst(rst),
    .ack(ack_sig),
    .req(req_sig),
    .data(data_sig),
    .done(done)
  );

  slave_fsm u_slave (
    .clk(clk),
    .rst(rst),
    .req(req_sig),
    .data_in(data_sig),
    .ack(ack_sig),
    .last_byte(last_byte_sig)
  );

endmodule

fsm-assignments/problem4_link/tb_link_top.v
`timescale 1ns/1ps
module tb_link_top;

  reg clk, rst;
  wire done;

  // DUT
  link_top dut (
    .clk(clk),
    .rst(rst),
    .done(done)
  );

  // Clock generator: 10 ns period
  initial begin
    clk = 0;
    forever #5 clk = ~clk;
  end

  // Reset generator
  initial begin
    rst = 1;
    #20;         // keep reset high for 20ns
    rst = 0;     // release reset
  end

  // Monitor signals (hierarchical references to FSMs)
  initial begin
    $dumpfile("handshake.vcd");    // for GTKWave
    $dumpvars(0, tb_link_top);

    $display(" Time | clk rst | req ack | data  last  | done");
    $monitor("%4t |  %b   %b  |  %b   %b  |  %h   %h  |  %b",
             $time, clk, rst,
             dut.u_master.req,
             dut.u_slave.ack,
             dut.u_master.data,
             dut.u_slave.last_byte,
             done);

    // Run until done goes high
    wait(done == 1);
    #20;  // observe done pulse
    $finish;
  end

endmodule

fsm-assignments/problem4_link/handshake.vcd
$date
	Mon Aug 18 23:57:17 2025
$end
$version
	Icarus Verilog
$end
$timescale
	1ps
$end
$scope module tb_link_top $end
$var wire 1 ! done $end
$var reg 1 " clk $end
$var reg 1 # rst $end
$scope module dut $end
$var wire 1 " clk $end
$var wire 1 # rst $end
$var wire 1 $ req_sig $end
$var wire 8 % last_byte_sig [7:0] $end
$var wire 1 ! done $end
$var wire 8 & data_sig [7:0] $end
$var wire 1 ' ack_sig $end
$scope module u_master $end
$var wire 1 " clk $end
$var wire 1 # rst $end
$var wire 1 ' ack $end
$var parameter 2 ( S_DONE $end
$var parameter 2 ) S_IDLE $end
$var parameter 2 * S_WAIT_ACK $end
$var parameter 2 + S_WAIT_ACK0 $end
$var reg 2 , byte_cnt [1:0] $end
$var reg 8 - data [7:0] $end
$var reg 1 ! done $end
$var reg 1 $ req $end
$var reg 2 . state [1:0] $end
$upscope $end
$scope module u_slave $end
$var wire 1 " clk $end
$var wire 8 / data_in [7:0] $end
$var wire 1 $ req $end
$var wire 1 # rst $end
$var parameter 2 0 S_DROP_ACK $end
$var parameter 2 1 S_HOLD_ACK $end
$var parameter 2 2 S_WAIT_REQ $end
$var reg 1 ' ack $end
$var reg 2 3 ack_cnt [1:0] $end
$var reg 8 4 last_byte [7:0] $end
$var reg 2 5 state [1:0] $end
$upscope $end
$upscope $end
$upscope $end
$enddefinitions $end
$comment Show the parameter values. $end
$dumpall
b0 2
b1 1
b10 0
b10 +
b1 *
b0 )
b11 (
$end
#0
$dumpvars
bx 5
bx 4
bx 3
bx /
bx .
bx -
bx ,
x'
bx &
bx %
x$
1#
0"
x!
$end
#5000
b0 ,
0!
0$
b0 .
b0 %
b0 4
b0 3
0'
b0 5
1"
#10000
0"
#15000
1"
#20000
0"
0#
#25000
b1 .
b10100000 &
b10100000 -
b10100000 /
1$
1"
#30000
0"
#35000
b1 5
1'
b10100000 %
b10100000 4
1"
#40000
0"
#45000
b10 .
0$
b1 3
1"
#50000
0"
#55000
b10 5
b10 3
1"
#60000
0"
#65000
b0 5
0'
1"
#70000
0"
#75000
b1 .
b10100001 &
b10100001 -
b10100001 /
1$
b1 ,
1"
#80000
0"
#85000
b1 5
b0 3
1'
b10100001 %
b10100001 4
1"
#90000
0"
#95000
b1 3
b10 .
0$
1"
#100000
0"
#105000
b10 5
b10 3
1"
#110000
0"
#115000
b0 5
0'
1"
#120000
0"
#125000
b1 .
b10100010 &
b10100010 -
b10100010 /
1$
b10 ,
1"
#130000
0"
#135000
b1 5
b0 3
1'
b10100010 %
b10100010 4
1"
#140000
0"
#145000
b10 .
0$
b1 3
1"
#150000
0"
#155000
b10 5
b10 3
1"
#160000
0"
#165000
b0 5
0'
1"
#170000
0"
#175000
b1 .
b10100011 &
b10100011 -
b10100011 /
1$
b11 ,
1"
#180000
0"
#185000
b1 5
b0 3
1'
b10100011 %
b10100011 4
1"
#190000
0"
#195000
b1 3
b10 .
0$
1"
#200000
0"
#205000
b10 5
b10 3
1"
#210000
0"
#215000
b0 5
0'
1"
#220000
0"
#225000
b11 .
b0 ,
1"
#230000
0"
#235000
b0 .
1!
1"
#240000
0"
#245000
b1 .
b10100000 &
b10100000 -
b10100000 /
1$
0!
1"
#250000
0"
#255000
b1 5
b0 3
1'
b10100000 %
b10100000 4
1"
