fsm-assignments/problem3_vending/vending_mealy.v
module vending_mealy (
    input clk,
    input reset,          // synchronous active-high reset
    input [1:0] coin,     // 01=5, 10=10, 00=idle (ignore 11)
    output dispense,      // 1-cycle pulse
    output chg5           // 1-cycle pulse when returning 5
);

    // State encoding
    reg [1:0] state_present, state_next;

    parameter s0  = 2'b00;   // total = 0
    parameter s5  = 2'b01;   // total = 5
    parameter s10 = 2'b10;   // total = 10
    parameter s15 = 2'b11;   // total = 15

    // Mealy combinational outputs
    reg dispense_mealy, chg5_mealy;

    // Registered outputs (guaranteed 1 cycle)
    reg dispense_ff = 0, chg5_ff = 0;  

    // State register (synchronous reset)
    always @(posedge clk) begin
        if (reset)
            state_present <= s0;
        else
            state_present <= state_next;
    end

    // Next state + Mealy outputs (combinational)
    always @(*) begin
        // default values
        state_next     = state_present;
        dispense_mealy = 0;
        chg5_mealy     = 0;

        case (state_present)
            s0: begin
                if (coin == 2'b01)       state_next = s5;
                else if (coin == 2'b10)  state_next = s10;
            end

            s5: begin
                if (coin == 2'b01)       state_next = s10;
                else if (coin == 2'b10)  state_next = s15;
            end

            s10: begin
                if (coin == 2'b01)       state_next = s15;
                else if (coin == 2'b10) begin
                    dispense_mealy = 1;   // vend
                    state_next     = s0;  // reset
                end
            end

            s15: begin
                if (coin == 2'b01) begin
                    dispense_mealy = 1;   // vend
                    state_next     = s0;
                end
                else if (coin == 2'b10) begin
                    dispense_mealy = 1;   // vend
                    chg5_mealy     = 1;   // change
                    state_next     = s0;
                end
            end

            default: state_next = s0;
        endcase
    end

    // Register the Mealy outputs -> guarantees 1-cycle pulses
    always @(posedge clk) begin
        if (reset) begin
            dispense_ff <= 0;
            chg5_ff     <= 0;
        end else begin
            dispense_ff <= dispense_mealy;
            chg5_ff     <= chg5_mealy;
        end
    end

    // Continuous assignment for final outputs
    assign dispense = dispense_ff;
    assign chg5     = chg5_ff;

endmodule

fsm-assignments/problem3_vending/tb_vending_mealy.v
`timescale 1ns/1ps
module tb_vending_mealy;

    reg clk, reset;
    reg [1:0] coin;
    wire dispense, chg5;

    // DUT
    vending_mealy dut(
        .clk(clk),
        .reset(reset),
        .coin(coin),
        .dispense(dispense),
        .chg5(chg5)
    );

    // Clock generation: 100MHz (10ns period)
    always #5 clk = ~clk;

    // Task: apply one coin for 1 cycle
    task insert_coin(input [1:0] c);
    begin
        coin = c;
        #10;           // hold for 1 clock
        coin = 2'b00;  // back to idle
        #10;
    end
    endtask

    initial begin
        // waveform dump
        $dumpfile("vending_mealy.vcd");
        $dumpvars(0, tb_vending_mealy);

        // init
        clk = 0; reset = 1; coin = 2'b00;
        #12 reset = 0;

        // ---- Test sequences ----

        // Case 1: 10 + 10 => vend
        insert_coin(2'b10);
        insert_coin(2'b10);

        // Case 2: 5 + 5 + 10 => vend
        insert_coin(2'b01);
        insert_coin(2'b01);
        insert_coin(2'b10);

        // Case 3: 15 (10+5) + 10 => vend + change
        insert_coin(2'b10);
        insert_coin(2'b01);
        insert_coin(2'b10);

        // Case 4: 5+5+5+5 => vend (all 5’s)
        insert_coin(2'b01);
        insert_coin(2'b01);
        insert_coin(2'b01);
        insert_coin(2'b01);

        // Case 5: 10 + 5 + 5 => vend
        insert_coin(2'b10);
        insert_coin(2'b01);
        insert_coin(2'b01);

        // Case 6: 5+5+5+10 => vend + change (25)
        insert_coin(2'b01);
        insert_coin(2'b01);
        insert_coin(2'b01);
        insert_coin(2'b10);

        // Case 7: Two purchases back-to-back
        insert_coin(2'b10);
        insert_coin(2'b10);   // first vend
        insert_coin(2'b01);
        insert_coin(2'b01);
        insert_coin(2'b10);   // second vend

        // Case 8: Random idle cycles between coins
        insert_coin(2'b10);
        #40;                  // wait idle
        insert_coin(2'b10);   // vend after gap

        // finish
        #100 $finish;
    end

endmodule

fsm-assignments/problem3_vending/vending_mealy.vcd
$date
	Sun Aug 17 23:55:53 2025
$end
$version
	Icarus Verilog
$end
$timescale
	1ps
$end
$scope module tb_vending_mealy $end
$var wire 1 ! dispense $end
$var wire 1 " chg5 $end
$var reg 1 # clk $end
$var reg 2 $ coin [1:0] $end
$var reg 1 % reset $end
$scope module dut $end
$var wire 1 " chg5 $end
$var wire 1 # clk $end
$var wire 2 & coin [1:0] $end
$var wire 1 ! dispense $end
$var wire 1 % reset $end
$var parameter 2 ' s0 $end
$var parameter 2 ( s10 $end
$var parameter 2 ) s15 $end
$var parameter 2 * s5 $end
$var reg 1 + chg5_ff $end
$var reg 1 , chg5_mealy $end
$var reg 1 - dispense_ff $end
$var reg 1 . dispense_mealy $end
$var reg 2 / state_next [1:0] $end
$var reg 2 0 state_present [1:0] $end
$upscope $end
$scope task insert_coin $end
$var reg 2 1 c [1:0] $end
$upscope $end
$upscope $end
$enddefinitions $end
$comment Show the parameter values. $end
$dumpall
b1 *
b11 )
b10 (
b0 '
$end
#0
$dumpvars
bx 1
bx 0
b0 /
0.
0-
0,
0+
b0 &
1%
b0 $
0#
0"
0!
$end
#5000
b0 0
1#
#10000
0#
#12000
b10 /
b10 $
b10 &
b10 1
0%
#15000
b0 /
1.
b10 0
1#
#20000
0#
#22000
0.
b10 /
b0 $
b0 &
#25000
1#
#30000
0#
#32000
b0 /
1.
b10 $
b10 &
#35000
b10 /
0.
1!
1-
b0 0
1#
#40000
0#
#42000
b0 /
b0 $
b0 &
#45000
0!
0-
1#
#50000
0#
#52000
b1 /
b1 $
b1 &
b1 1
#55000
b10 /
b1 0
1#
#60000
0#
#62000
b1 /
b0 $
b0 &
#65000
1#
#70000
0#
#72000
b10 /
b1 $
b1 &
#75000
b11 /
b10 0
1#
#80000
0#
#82000
b10 /
b0 $
b0 &
#85000
1#
#90000
0#
#92000
b0 /
1.
b10 $
b10 &
b10 1
#95000
b10 /
0.
1!
1-
b0 0
1#
#100000
0#
#102000
b0 /
b0 $
b0 &
#105000
0!
0-
1#
#110000
0#
#112000
b10 /
b10 $
b10 &
#115000
b0 /
1.
b10 0
1#
#120000
0#
#122000
0.
b10 /
b0 $
b0 &
#125000
1#
#130000
0#
#132000
b11 /
b1 $
b1 &
b1 1
#135000
b0 /
1.
b11 0
1#
#140000
0#
#142000
0.
b11 /
b0 $
b0 &
#145000
1#
#150000
0#
#152000
b0 /
1,
1.
b10 $
b10 &
b10 1
#155000
b10 /
0,
0.
1"
1+
1!
1-
b0 0
1#
#160000
0#
#162000
b0 /
b0 $
b0 &
#165000
0"
0+
0!
0-
1#
#170000
0#
#172000
b1 /
b1 $
b1 &
b1 1
#175000
b10 /
b1 0
1#
#180000
0#
#182000
b1 /
b0 $
b0 &
#185000
1#
#190000
0#
#192000
b10 /
b1 $
b1 &
#195000
b11 /
b10 0
1#
#200000
0#
#202000
b10 /
b0 $
b0 &
#205000
1#
#210000
0#
#212000
b11 /
b1 $
b1 &
#215000
b0 /
1.
b11 0
1#
#220000
0#
#222000
0.
b11 /
b0 $
b0 &
#225000
1#
#230000
0#
#232000
b0 /
1.
b1 $
b1 &
#235000
b1 /
0.
1!
1-
b0 0
1#
#240000
0#
#242000
b0 /
b0 $
b0 &
#245000
0!
0-
1#
#250000
0#
#252000
b10 /
b10 $
b10 &
b10 1
#255000
b0 /
1.
b10 0
1#
#260000
0#
#262000
0.
b10 /
b0 $
b0 &
#265000
1#
#270000
0#
#272000
b11 /
b1 $
b1 &
b1 1
#275000
b0 /
1.
b11 0
1#
#280000
0#
#282000
0.
b11 /
b0 $
b0 &
#285000
1#
#290000
0#
#292000
b0 /
1.
b1 $
b1 &
#295000
b1 /
0.
1!
1-
b0 0
1#
#300000
0#
#302000
b0 /
b0 $
b0 &
#305000
0!
0-
1#
#310000
0#
#312000
b1 /
b1 $
b1 &
#315000
b10 /
b1 0
1#
#320000
0#
#322000
b1 /
b0 $
b0 &
#325000
1#
#330000
0#
#332000
b10 /
b1 $
b1 &
#335000
b11 /
b10 0
1#
#340000
0#
#342000
b10 /
b0 $
b0 &
#345000
1#
#350000
0#
#352000
b11 /
b1 $
b1 &
#355000
b0 /
1.
b11 0
1#
#360000
0#
#362000
0.
b11 /
b0 $
b0 &
#365000
1#
#370000
0#
#372000
b0 /
1,
1.
b10 $
b10 &
b10 1
#375000
b10 /
0,
0.
1"
1+
1!
1-
b0 0
1#
#380000
0#
#382000
b0 /
b0 $
b0 &
#385000
0"
0+
0!
0-
1#
#390000
0#
#392000
b10 /
b10 $
b10 &
#395000
b0 /
1.
b10 0
1#
#400000
0#
#402000
0.
b10 /
b0 $
b0 &
#405000
1#
#410000
0#
#412000
b0 /
1.
b10 $
b10 &
#415000
b10 /
0.
1!
1-
b0 0
1#
#420000
0#
#422000
b0 /
b0 $
b0 &
#425000
0!
0-
1#
#430000
0#
#432000
b1 /
b1 $
b1 &
b1 1
#435000
b10 /
b1 0
1#
#440000
0#
#442000
b1 /
b0 $
b0 &
#445000
1#
#450000
0#
#452000
b10 /
b1 $
b1 &
#455000
b11 /
b10 0
1#
#460000
0#
#462000
b10 /
b0 $
b0 &
#465000
1#
#470000
0#
#472000
b0 /
1.
b10 $
b10 &
b10 1
#475000
b10 /
0.
1!
1-
b0 0
1#
#480000
0#
#482000
b0 /
b0 $
b0 &
#485000
0!
0-
1#
#490000
0#
#492000
b10 /
b10 $
b10 &
#495000
b0 /
1.
b10 0
1#
#500000
0#
#502000
0.
b10 /
b0 $
b0 &
#505000
1#
#510000
0#
#515000
1#
#520000
0#
#525000
1#
#530000
0#
#535000
1#
#540000
0#
#545000
1#
#550000
0#
#552000
b0 /
1.
b10 $
b10 &
#555000
b10 /
0.
1!
1-
b0 0
1#
#560000
0#
#562000
b0 /
b0 $
b0 &
#565000
0!
0-
1#
