fsm-assignments/problem1_seqdet/seq_detect_mealy.v
module seq_detect_mealy (
  input  clk,
  input  rst,    // synchronous, active-high
  input  din,    // serial input bit per clock
  output y       // 1-cycle pulse when pattern ...1101 seen
);

  reg [1:0] state_present, state_next;

  // State encoding
  parameter init    = 2'b00;
  parameter got_1   = 2'b01;
  parameter got_11  = 2'b10;
  parameter got_110 = 2'b11;

  // State register (synchronous reset)
  always @ (posedge clk) begin
    if (rst) state_present <= init;       // sync active-high reset
    else     state_present <= state_next; // move to next state
  end

  // Next-state logic
  always @ (*) begin
    case (state_present)
      init:    state_next = din ? got_1   : init;
      got_1:   state_next = din ? got_11  : init;
      got_11:  state_next = din ? got_11  : got_110;
      got_110: state_next = din ? got_1   : init; // detection → fallback to got_1 for overlap
      default: state_next = init; // safety default
    endcase
  end

  // Output logic (Mealy: depends on present state + input)
  assign y = (state_present == got_110) && din;

endmodule

fsm-assignments/problem1_seqdet/tb_seq_detect_mealy.v
module tb_seq_detect_mealy;
    reg clk, rst, din;
    wire y;

    seq_detect_mealy dut (
        .clk(clk),
        .rst(rst),
        .din(din),
        .y(y)
    );

    // Clock generation (100 MHz -> 10 ns period)
    always #5 clk = ~clk;

    initial begin
        $dumpfile("dump.vcd");
        $dumpvars(0, tb_seq_detect_mealy);

        // Initialize
        clk = 0;
        rst = 1;
        din = 0;
        #10;
        rst = 0;

        // Test input stream: 11011011101
        din = 1; #10;
        din = 1; #10;
        din = 0; #10;
        din = 1; #10;
        din = 1; #10;
        din = 0; #10;
        din = 1; #10;
        din = 1; #10;
        din = 1; #10;
        din = 0; #10;
        din = 1; #10;

        // Case 2: with synchronous reset in the middle
        din = 1; #10;
        din = 1; #10;
        rst = 1; #10;   // assert synchronous reset on clock edge
        rst = 0; #10;   // deassert reset, FSM restarts from init
        din = 0; #10;
        din = 1; #10;
        din = 1; #10;
        din = 0; #10;
        din = 1; #10;

        #20 $finish;
    end
endmodule

fsm-assignments/problem1_seqdet/dump.vcd
$date
	Sun Aug 17 22:51:45 2025
$end
$version
	Icarus Verilog
$end
$timescale
	1s
$end
$scope module tb_seq_detect_mealy $end
$var wire 1 ! y $end
$var reg 1 " clk $end
$var reg 1 # din $end
$var reg 1 $ rst $end
$scope module dut $end
$var wire 1 " clk $end
$var wire 1 # din $end
$var wire 1 $ rst $end
$var wire 1 ! y $end
$var parameter 2 % got_1 $end
$var parameter 2 & got_11 $end
$var parameter 2 ' got_110 $end
$var parameter 2 ( init $end
$var reg 2 ) state_next [1:0] $end
$var reg 2 * state_present [1:0] $end
$upscope $end
$upscope $end
$enddefinitions $end
$comment Show the parameter values. $end
$dumpall
b0 (
b11 '
b10 &
b1 %
$end
#0
$dumpvars
bx *
b0 )
1$
0#
0"
0!
$end
#5
b0 *
1"
#10
b1 )
0"
1#
0$
#15
b10 )
b1 *
1"
#20
0"
#25
b10 *
1"
#30
b11 )
0"
0#
#35
b0 )
b11 *
1"
#40
1!
b1 )
0"
1#
#45
b10 )
0!
b1 *
1"
#50
0"
#55
b10 *
1"
#60
b11 )
0"
0#
#65
b0 )
b11 *
1"
#70
1!
b1 )
0"
1#
#75
b10 )
0!
b1 *
1"
#80
0"
#85
b10 *
1"
#90
0"
#95
1"
#100
b11 )
0"
0#
#105
b0 )
b11 *
1"
#110
1!
b1 )
0"
1#
#115
b10 )
0!
b1 *
1"
#120
0"
#125
b10 *
1"
#130
0"
#135
1"
#140
0"
1$
#145
b1 )
b0 *
1"
#150
0"
0$
#155
b10 )
b1 *
1"
#160
b0 )
0"
0#
#165
b0 *
1"
#170
b1 )
0"
1#
#175
b10 )
b1 *
1"
#180
0"
#185
b10 *
1"
#190
b11 )
0"
0#
#195
b0 )
b11 *
1"
#200
1!
b1 )
0"
1#
#205
b10 )
0!
b1 *
1"
#210
0"
#215
b10 *
1"
