rvx10p_230102091/src/dmem.sv
module dmem(input logic clk, we,
            input  logic [31:0] a, wd,
            output logic [31:0] rd);
    logic [31:0] mem[0:255];
    always_ff @(posedge clk)
        if (we) mem[a[9:2]] <= wd;
    assign rd = mem[a[9:2]];
endmodule

rvx10p_230102091/src/imem.sv
module imem(input  logic [7:0]  a,
            output logic [31:0] rd);
    logic [31:0] mem [0:255];

    initial begin
        $readmemh("tests/rvx10_pipeline.hex", mem);
        $display("Instruction memory loaded.");
    end

    assign rd = mem[a];
endmodule

rvx10p_230102091/src/alu.sv
module alu(
    input  logic [31:0] a, b,
    input  logic [3:0] alucontrol,
    output logic [31:0] result,
    output logic zero
);
    always_comb begin
        case (alucontrol)
            4'b0000: result = a + b;   // ADD
            4'b0001: result = a - b;   // SUB
            4'b0010: result = a & b;   // AND
            4'b0011: result = a | b;   // OR
            4'b0100: result = a ^ b;   // XOR
            4'b0101: result = a << b[4:0]; // SLL
            4'b0110: result = a >> b[4:0]; // SRL
            4'b0111: result = ($signed(a) < $signed(b)) ? a : b; // MIN (RVX10)
            4'b1000: result = (a < b) ? b : a; // MAX (RVX10)
            default: result = 32'b0;
        endcase
        zero = (result == 0);
    end
endmodule

rvx10p_230102091/src/regfile.sv
module regfile(
    input  logic clk, we3,
    input  logic [4:0] a1, a2, a3,
    input  logic [31:0] wd3,
    output logic [31:0] rd1, rd2
);
    logic [31:0] rf [31:0];
    assign rd1 = (a1 != 0) ? rf[a1] : 0;
    assign rd2 = (a2 != 0) ? rf[a2] : 0;
    always_ff @(posedge clk)
        if (we3 && a3 != 0)
            rf[a3] <= wd3;
endmodule

rvx10p_230102091/src/datapath.sv
module datapath(
    input  logic clk, reset,
    input  logic memtoregD, memwriteD, branchD, alusrcD, regwriteD, jumpD,
    input  logic [3:0] alucontrolD,
    input  logic [31:0] instr, readdataM,
    output logic memwriteM,
    output logic [31:0] aluoutM, writedataM, pcF
);
    // --- IF stage ---
    logic [31:0] pcnext, pcplus4;
    logic [31:0] instrD;
    assign pcplus4 = pcF + 4;

    always_ff @(posedge clk or posedge reset)
        if (reset) pcF <= 0;
        else pcF <= pcnext;

    // IF/ID
    always_ff @(posedge clk) instrD <= instr;

    // --- ID stage ---
    logic [31:0] rd1D, rd2D, immD;
    logic [4:0] rs1D, rs2D, rdD;
    assign rs1D = instrD[19:15];
    assign rs2D = instrD[24:20];
    assign rdD  = instrD[11:7];

    regfile rf (.clk(clk), .we3(regwriteD),
                .a1(rs1D), .a2(rs2D), .a3(rdD),
                .wd3(32'b0), // simplified
                .rd1(rd1D), .rd2(rd2D));

    assign immD = {{20{instrD[31]}}, instrD[31:20]}; // simple imm

    // --- EX stage ---
    logic [31:0] srcA, srcB, aluoutE;
    logic zero;
    assign srcA = rd1D;
    assign srcB = (alusrcD) ? immD : rd2D;

    alu alu_inst (.a(srcA), .b(srcB), .alucontrol(alucontrolD), .result(aluoutE), .zero(zero));

    // --- MEM stage ---
    assign aluoutM = aluoutE;
    assign writedataM = rd2D;
    assign memwriteM = memwriteD;

    // --- WB stage (skipped for simplicity) ---
    assign pcnext = pcplus4; // no branch yet
endmodule

rvx10p_230102091/src/aludec.sv
module aludec(
    input  logic [2:0] funct3,
    input  logic [6:0] funct7,
    input  logic [1:0] aluop,
    output logic [3:0] alucontrol
);
    always_comb begin
        case (aluop)
            2'b00: alucontrol = 4'b0000; // for load/store: add
            2'b01: alucontrol = 4'b0001; // for branch: subtract
            2'b10: begin // R-type
                case ({funct7, funct3})
                    10'b0000000_000: alucontrol = 4'b0000; // ADD
                    10'b0100000_000: alucontrol = 4'b0001; // SUB
                    10'b0000000_111: alucontrol = 4'b0010; // AND
                    10'b0000000_110: alucontrol = 4'b0011; // OR
                    10'b0000000_100: alucontrol = 4'b0100; // XOR
                    10'b0000000_001: alucontrol = 4'b0101; // SLL
                    10'b0000000_101: alucontrol = 4'b0110; // SRL
                    // RVX10 Custom
                    10'b0000001_000: alucontrol = 4'b0111; // MIN
                    10'b0000001_001: alucontrol = 4'b1000; // MAX
                    default: alucontrol = 4'b0000;
                endcase
            end
            2'b11: begin // I-type arithmetic (addi, andi, ori)
                case (funct3)
                    3'b000: alucontrol = 4'b0000; // ADDI
                    3'b111: alucontrol = 4'b0010; // ANDI
                    3'b110: alucontrol = 4'b0011; // ORI
                    default: alucontrol = 4'b0000;
                endcase
            end
            default: alucontrol = 4'b0000;
        endcase
    end
endmodule

rvx10p_230102091/src/maindec.sv
module maindec(
    input  logic [6:0] op,
    output logic memtoreg, memwrite, branch, alusrc, regwrite, jump,
    output logic [1:0] aluop
);
    always_comb begin
        // Default (NOP)
        memtoreg = 0;
        memwrite = 0;
        branch   = 0;
        alusrc   = 0;
        regwrite = 0;
        jump     = 0;
        aluop    = 2'b00;

        case (op)
            7'b0110011: begin // R-type (add, sub, and, or, etc.)
                regwrite = 1;
                aluop = 2'b10;
            end
            7'b0010011: begin // I-type (addi, andi, ori, etc.)
                regwrite = 1;
                alusrc = 1;
                aluop = 2'b11;
            end
            7'b0000011: begin // LW
                memtoreg = 1;
                regwrite = 1;
                alusrc = 1;
                aluop = 2'b00;
            end
            7'b0100011: begin // SW
                memwrite = 1;
                alusrc = 1;
                aluop = 2'b00;
            end
            7'b1100011: begin // BEQ/BNE
                branch = 1;
                aluop = 2'b01;
            end
            7'b1101111: begin // JAL
                jump = 1;
                regwrite = 1;
            end
            default: ; // keep defaults
        endcase
    end
endmodule

rvx10p_230102091/src/controller.sv
module controller(
    input  logic [6:0] op,
    input  logic [2:0] funct3,
    input  logic [6:0] funct7,
    output logic memtoreg, memwrite, branch, alusrc, regwrite, jump,
    output logic [3:0] alucontrol
);
    logic [1:0] aluop;

    maindec md(op, memtoreg, memwrite, branch, alusrc, regwrite, jump, aluop);
    aludec ad(funct3, funct7, aluop, alucontrol);
endmodule

rvx10p_230102091/src/riscvpipeline.sv
module riscvpipeline (
    input  logic clk,
    input  logic reset
);
    // Instruction and data memory
    logic [31:0] instr, read_data;
    logic [31:0] pcF;
    logic memwriteM;
    logic [31:0] alu_outM, writedataM;

    // Instantiate datapath and controller
    logic memtoregD, memtoregE, memtoregM, memtoregW;
    logic memwriteD, memwriteE, regwriteD, regwriteE, regwriteM, regwriteW;
    logic alusrcD, alusrcE, branchD, branchE, jumpD, jumpE;
    logic [3:0] alucontrolD, alucontrolE;

    controller c(
        .op(instr[6:0]),
        .funct3(instr[14:12]),
        .funct7(instr[31:25]),
        .memtoreg(memtoregD),
        .memwrite(memwriteD),
        .branch(branchD),
        .alusrc(alusrcD),
        .regwrite(regwriteD),
        .jump(jumpD),
        .alucontrol(alucontrolD)
    );

    datapath dp(
        .clk(clk),
        .reset(reset),
        .memtoregD(memtoregD),
        .memwriteD(memwriteD),
        .branchD(branchD),
        .alusrcD(alusrcD),
        .regwriteD(regwriteD),
        .jumpD(jumpD),
        .alucontrolD(alucontrolD),
        .instr(instr),
        .readdataM(read_data),
        .memwriteM(memwriteM),
        .aluoutM(alu_outM),
        .writedataM(writedataM),
        .pcF(pcF)
    );

    // Instruction Memory (example behavioral)
    imem imem_inst (.a(pcF[9:2]), .rd(instr));

    // Data Memory
    dmem dmem_inst (.clk(clk), .we(memwriteM),
                    .a(alu_outM), .wd(writedataM), .rd(read_data));
endmodule

rvx10p_230102091/tb/tb_pipeline.sv
module tb_pipeline;
    logic clk = 0, reset = 1;
    riscvpipeline dut (.clk(clk), .reset(reset));

    always #5 clk = ~clk;

    initial begin
        $dumpfile("dump.vcd");
        $dumpvars(0, tb_pipeline);
        #20 reset = 0;
        #2000 $finish;
    end
endmodule

rvx10p_230102091/dump.vcd
$date
	Thu Oct 30 22:48:17 2025
$end
$version
	Icarus Verilog
$end
$timescale
	1s
$end
$scope module tb_pipeline $end
$var reg 1 ! clk $end
$var reg 1 " reset $end
$scope module dut $end
$var wire 1 ! clk $end
$var wire 1 " reset $end
$var wire 32 # writedataM [31:0] $end
$var wire 1 $ regwriteD $end
$var wire 32 % read_data [31:0] $end
$var wire 32 & pcF [31:0] $end
$var wire 1 ' memwriteM $end
$var wire 1 ( memwriteD $end
$var wire 1 ) memtoregD $end
$var wire 1 * jumpD $end
$var wire 32 + instr [31:0] $end
$var wire 1 , branchD $end
$var wire 1 - alusrcD $end
$var wire 4 . alucontrolD [3:0] $end
$var wire 32 / alu_outM [31:0] $end
$scope module c $end
$var wire 3 0 funct3 [2:0] $end
$var wire 7 1 funct7 [6:0] $end
$var wire 7 2 op [6:0] $end
$var wire 1 $ regwrite $end
$var wire 1 ( memwrite $end
$var wire 1 ) memtoreg $end
$var wire 1 * jump $end
$var wire 1 , branch $end
$var wire 1 - alusrc $end
$var wire 2 3 aluop [1:0] $end
$var wire 4 4 alucontrol [3:0] $end
$scope module ad $end
$var wire 3 5 funct3 [2:0] $end
$var wire 7 6 funct7 [6:0] $end
$var wire 2 7 aluop [1:0] $end
$var reg 4 8 alucontrol [3:0] $end
$upscope $end
$scope module md $end
$var wire 7 9 op [6:0] $end
$var reg 2 : aluop [1:0] $end
$var reg 1 - alusrc $end
$var reg 1 , branch $end
$var reg 1 * jump $end
$var reg 1 ) memtoreg $end
$var reg 1 ( memwrite $end
$var reg 1 $ regwrite $end
$upscope $end
$upscope $end
$scope module dmem_inst $end
$var wire 1 ! clk $end
$var wire 32 ; rd [31:0] $end
$var wire 1 ' we $end
$var wire 32 < wd [31:0] $end
$var wire 32 = a [31:0] $end
$upscope $end
$scope module dp $end
$var wire 4 > alucontrolD [3:0] $end
$var wire 32 ? aluoutM [31:0] $end
$var wire 1 - alusrcD $end
$var wire 1 , branchD $end
$var wire 1 ! clk $end
$var wire 1 * jumpD $end
$var wire 1 ) memtoregD $end
$var wire 1 ( memwriteD $end
$var wire 1 ' memwriteM $end
$var wire 32 @ pcnext [31:0] $end
$var wire 32 A readdataM [31:0] $end
$var wire 1 $ regwriteD $end
$var wire 1 " reset $end
$var wire 32 B srcA [31:0] $end
$var wire 32 C writedataM [31:0] $end
$var wire 1 D zero $end
$var wire 32 E srcB [31:0] $end
$var wire 5 F rs2D [4:0] $end
$var wire 5 G rs1D [4:0] $end
$var wire 5 H rdD [4:0] $end
$var wire 32 I rd2D [31:0] $end
$var wire 32 J rd1D [31:0] $end
$var wire 32 K pcplus4 [31:0] $end
$var wire 32 L instr [31:0] $end
$var wire 32 M immD [31:0] $end
$var wire 32 N aluoutE [31:0] $end
$var reg 32 O instrD [31:0] $end
$var reg 32 P pcF [31:0] $end
$scope module alu_inst $end
$var wire 32 Q a [31:0] $end
$var wire 4 R alucontrol [3:0] $end
$var wire 32 S b [31:0] $end
$var reg 32 T result [31:0] $end
$var reg 1 D zero $end
$upscope $end
$scope module rf $end
$var wire 5 U a1 [4:0] $end
$var wire 5 V a2 [4:0] $end
$var wire 5 W a3 [4:0] $end
$var wire 1 ! clk $end
$var wire 32 X wd3 [31:0] $end
$var wire 1 $ we3 $end
$var wire 32 Y rd2 [31:0] $end
$var wire 32 Z rd1 [31:0] $end
$upscope $end
$upscope $end
$scope module imem_inst $end
$var wire 8 [ a [7:0] $end
$var wire 32 \ rd [31:0] $end
$upscope $end
$upscope $end
$upscope $end
$enddefinitions $end
$comment Show the parameter values. $end
$dumpall
$end
#0
$dumpvars
bx \
bx [
bx Z
bx Y
b0 X
bx W
bx V
bx U
bx T
bx S
b0 R
bx Q
bx P
bx O
bx N
bx M
bx L
bx K
bx J
bx I
bx H
bx G
bx F
bx E
xD
bx C
bx B
bx A
bx @
bx ?
b0 >
bx =
bx <
bx ;
b0 :
bx 9
b0 8
b0 7
bx 6
bx 5
b0 4
b0 3
bx 2
bx 1
bx 0
bx /
b0 .
0-
0,
bx +
0*
0)
0(
0'
bx &
bx %
0$
bx #
1"
0!
$end
#5
b11 3
b11 7
b11 :
1-
1$
b0 1
b0 6
b0 0
b0 5
b10011 2
b10011 9
b10010011 +
b10010011 L
b10010011 \
b0 [
b100 @
b100 K
b0 &
b0 P
1!
#10
0!
#15
1D
b0 /
b0 =
b0 ?
b0 N
b0 T
b0 B
b0 Q
b0 J
b0 Z
b0 #
b0 <
b0 C
b0 I
b0 Y
b0 E
b0 S
b0 G
b0 U
b0 F
b0 V
b1 H
b1 W
b0 M
b10010011 O
1!
#20
0!
0"
#25
b100000000000100010011 +
b100000000000100010011 L
b100000000000100010011 \
b1 [
b1000 @
b1000 K
b100 &
b100 P
1!
#30
0!
#35
1D
b0 /
b0 =
b0 ?
b0 N
b0 T
b10 3
b10 7
b10 :
1$
0-
b0 E
b0 S
b110011 2
b110011 9
b1 F
b1 V
b10 H
b10 W
b1 M
b1000001000000110110011 +
b1000001000000110110011 L
b1000001000000110110011 \
b10 [
b100000000000100010011 O
b1100 @
b1100 K
b1000 &
b1000 P
1!
#40
0!
#45
b1 G
b1 U
b10 F
b10 V
b11 H
b11 W
b10 M
b1100010000001000110011 +
b1100010000001000110011 L
b1100010000001000110011 \
b11 [
b1000001000000110110011 O
b10000 @
b10000 K
b1100 &
b1100 P
1!
#50
0!
#55
b10 G
b10 U
b11 F
b11 V
b100 H
b100 W
b11 M
b10000011000001010110011 +
b10000011000001010110011 L
b10000011000001010110011 \
b100 [
b1100010000001000110011 O
b10100 @
b10100 K
b10000 &
b10000 P
1!
#60
0!
#65
b11 G
b11 U
b100 F
b100 V
b101 H
b101 W
b100 M
b10100100000001100110011 +
b10100100000001100110011 L
b10100100000001100110011 \
b101 [
b10000011000001010110011 O
b11000 @
b11000 K
b10100 &
b10100 P
1!
#70
0!
#75
b100 G
b100 U
b101 F
b101 V
b110 H
b110 W
b101 M
b11000101000001110110011 +
b11000101000001110110011 L
b11000101000001110110011 \
b110 [
b10100100000001100110011 O
b11100 @
b11100 K
b11000 &
b11000 P
1!
#80
0!
#85
b101 G
b101 U
b110 F
b110 V
b111 H
b111 W
b110 M
b11100110000010000110011 +
b11100110000010000110011 L
b11100110000010000110011 \
b111 [
b11000101000001110110011 O
b100000 @
b100000 K
b11100 &
b11100 P
1!
#90
0!
#95
0D
b111 /
b111 =
b111 ?
b111 N
b111 T
b111 E
b111 S
1-
1)
b0 3
b0 7
b0 :
1$
b10 0
b10 5
b11 2
b11 9
b110 G
b110 U
b111 F
b111 V
b1000 H
b1000 W
b111 M
b110010010010000011 +
b110010010010000011 L
b110010010010000011 \
b1000 [
b11100110000010000110011 O
b100100 @
b100100 K
b100000 &
b100000 P
1!
#100
0!
#105
1D
b0 /
b0 =
b0 ?
b0 N
b0 T
b10 3
b10 7
b10 :
1$
0-
0)
b0 E
b0 S
b0 0
b0 5
b110011 2
b110011 9
b0 F
b0 V
b1001 H
b1001 W
b0 M
b100101000000010100110011 +
b100101000000010100110011 L
b100101000000010100110011 \
b1001 [
b110010010010000011 O
b101000 @
b101000 K
b100100 &
b100100 P
1!
#110
0!
#115
b1 .
b1 4
b1 8
b1 >
b1 R
1,
b1 3
b1 7
b1 :
0$
b1100011 2
b1100011 9
b1000 G
b1000 U
b1001 F
b1001 V
b1010 H
b1010 W
b1001 M
b101001010000000001100011 +
b101001010000000001100011 L
b101001010000000001100011 \
b1010 [
b100101000000010100110011 O
b101100 @
b101100 K
b101000 &
b101000 P
1!
#120
0!
#125
b0 .
b0 4
b0 8
b0 >
b0 R
xD
bx /
bx =
bx ?
bx N
bx T
bx E
bx S
1$
b10 3
b10 7
b10 :
0,
bx B
bx Q
bx J
bx Z
bx #
bx <
bx C
bx I
bx Y
b110011 2
b110011 9
b1010 G
b1010 U
b1010 F
b1010 V
b0 H
b0 W
b1010 M
b101101010000010010110011 +
b101101010000010010110011 L
b101101010000010010110011 \
b1011 [
b101001010000000001100011 O
b110000 @
b110000 K
b101100 &
b101100 P
1!
#130
0!
#135
1*
b0 3
b0 7
b0 :
1$
b1101111 2
b1101111 9
b1011 F
b1011 V
b1001 H
b1001 W
b1011 M
b1101111 +
b1101111 L
b1101111 \
b1100 [
b101101010000010010110011 O
b110100 @
b110100 K
b110000 &
b110000 P
1!
#140
0!
#145
1D
b0 /
b0 =
b0 ?
b0 N
b0 T
b0 E
b0 S
0*
0$
b0 B
b0 Q
b0 J
b0 Z
b0 #
b0 <
b0 C
b0 I
b0 Y
bx 1
bx 6
bx 0
bx 5
bx 2
bx 9
b0 G
b0 U
b0 F
b0 V
b0 H
b0 W
b0 M
bx +
bx L
bx \
b1101 [
b1101111 O
b111000 @
b111000 K
b110100 &
b110100 P
1!
#150
0!
#155
xD
bx /
bx =
bx ?
bx N
bx T
bx E
bx S
bx B
bx Q
bx J
bx Z
bx #
bx <
bx C
bx I
bx Y
bx G
bx U
bx F
bx V
bx H
bx W
bx M
b1110 [
bx O
b111100 @
b111100 K
b111000 &
b111000 P
1!
#160
0!
#165
b1111 [
b1000000 @
b1000000 K
b111100 &
b111100 P
1!
#170
0!
#175
b10000 [
b1000100 @
b1000100 K
b1000000 &
b1000000 P
1!
#180
0!
#185
b10001 [
b1001000 @
b1001000 K
b1000100 &
b1000100 P
1!
#190
0!
#195
b10010 [
b1001100 @
b1001100 K
b1001000 &
b1001000 P
1!
#200
0!
#205
b10011 [
b1010000 @
b1010000 K
b1001100 &
b1001100 P
1!
#210
0!
#215
b10100 [
b1010100 @
b1010100 K
b1010000 &
b1010000 P
1!
#220
0!
#225
b10101 [
b1011000 @
b1011000 K
b1010100 &
b1010100 P
1!
#230
0!
#235
b10110 [
b1011100 @
b1011100 K
b1011000 &
b1011000 P
1!
#240
0!
#245
b10111 [
b1100000 @
b1100000 K
b1011100 &
b1011100 P
1!
#250
0!
#255
b11000 [
b1100100 @
b1100100 K
b1100000 &
b1100000 P
1!
#260
0!
#265
b11001 [
b1101000 @
b1101000 K
b1100100 &
b1100100 P
1!
#270
0!
#275
b11010 [
b1101100 @
b1101100 K
b1101000 &
b1101000 P
1!
#280
0!
#285
b11011 [
b1110000 @
b1110000 K
b1101100 &
b1101100 P
1!
#290
0!
#295
b11100 [
b1110100 @
b1110100 K
b1110000 &
b1110000 P
1!
#300
0!
#305
b11101 [
b1111000 @
b1111000 K
b1110100 &
b1110100 P
1!
#310
0!
#315
b11110 [
b1111100 @
b1111100 K
b1111000 &
b1111000 P
1!
#320
0!
#325
b11111 [
b10000000 @
b10000000 K
b1111100 &
b1111100 P
1!
#330
0!
#335
b100000 [
b10000100 @
b10000100 K
b10000000 &
b10000000 P
1!
#340
0!
#345
b100001 [
b10001000 @
b10001000 K
b10000100 &
b10000100 P
1!
#350
0!
#355
b100010 [
b10001100 @
b10001100 K
b10001000 &
b10001000 P
1!
#360
0!
#365
b100011 [
b10010000 @
b10010000 K
b10001100 &
b10001100 P
1!
#370
0!
#375
b100100 [
b10010100 @
b10010100 K
b10010000 &
b10010000 P
1!
#380
0!
#385
b100101 [
b10011000 @
b10011000 K
b10010100 &
b10010100 P
1!
#390
0!
#395
b100110 [
b10011100 @
b10011100 K
b10011000 &
b10011000 P
1!
#400
0!
#405
b100111 [
b10100000 @
b10100000 K
b10011100 &
b10011100 P
1!
#410
0!
#415
b101000 [
b10100100 @
b10100100 K
b10100000 &
b10100000 P
1!
#420
0!
#425
b101001 [
b10101000 @
b10101000 K
b10100100 &
b10100100 P
1!
#430
0!
#435
b101010 [
b10101100 @
b10101100 K
b10101000 &
b10101000 P
1!
#440
0!
#445
b101011 [
b10110000 @
b10110000 K
b10101100 &
b10101100 P
1!
#450
0!
#455
b101100 [
b10110100 @
b10110100 K
b10110000 &
b10110000 P
1!
#460
0!
#465
b101101 [
b10111000 @
b10111000 K
b10110100 &
b10110100 P
1!
#470
0!
#475
b101110 [
b10111100 @
b10111100 K
b10111000 &
b10111000 P
1!
#480
0!
#485
b101111 [
b11000000 @
b11000000 K
b10111100 &
b10111100 P
1!
#490
0!
#495
b110000 [
b11000100 @
b11000100 K
b11000000 &
b11000000 P
1!
#500
0!
#505
b110001 [
b11001000 @
b11001000 K
b11000100 &
b11000100 P
1!
#510
0!
#515
b110010 [
b11001100 @
b11001100 K
b11001000 &
b11001000 P
1!
#520
0!
#525
b110011 [
b11010000 @
b11010000 K
b11001100 &
b11001100 P
1!
#530
0!
#535
b110100 [
b11010100 @
b11010100 K
b11010000 &
b11010000 P
1!
#540
0!
#545
b110101 [
b11011000 @
b11011000 K
b11010100 &
b11010100 P
1!
#550
0!
#555
b110110 [
b11011100 @
b11011100 K
b11011000 &
b11011000 P
1!
#560
0!
#565
b110111 [
b11100000 @
b11100000 K
b11011100 &
b11011100 P
1!
#570
0!
#575
b111000 [
b11100100 @
b11100100 K
b11100000 &
b11100000 P
1!
#580
0!
#585
b111001 [
b11101000 @
b11101000 K
b11100100 &
b11100100 P
1!
#590
0!
#595
b111010 [
b11101100 @
b11101100 K
b11101000 &
b11101000 P
1!
#600
0!
#605
b111011 [
b11110000 @
b11110000 K
b11101100 &
b11101100 P
1!
#610
0!
#615
b111100 [
b11110100 @
b11110100 K
b11110000 &
b11110000 P
1!
#620
0!
#625
b111101 [
b11111000 @
b11111000 K
b11110100 &
b11110100 P
1!
#630
0!
#635
b111110 [
b11111100 @
b11111100 K
b11111000 &
b11111000 P
1!
#640
0!
#645
b111111 [
b100000000 @
b100000000 K
b11111100 &
b11111100 P
1!
#650
0!
#655
b1000000 [
b100000100 @
b100000100 K
b100000000 &
b100000000 P
1!
#660
0!
#665
b1000001 [
b100001000 @
b100001000 K
b100000100 &
b100000100 P
1!
#670
0!
#675
b1000010 [
b100001100 @
b100001100 K
b100001000 &
b100001000 P
1!
#680
0!
#685
b1000011 [
b100010000 @
b100010000 K
b100001100 &
b100001100 P
1!
#690
0!
#695
b1000100 [
b100010100 @
b100010100 K
b100010000 &
b100010000 P
1!
#700
0!
#705
b1000101 [
b100011000 @
b100011000 K
b100010100 &
b100010100 P
1!
#710
0!
#715
b1000110 [
b100011100 @
b100011100 K
b100011000 &
b100011000 P
1!
#720
0!
#725
b1000111 [
b100100000 @
b100100000 K
b100011100 &
b100011100 P
1!
#730
0!
#735
b1001000 [
b100100100 @
b100100100 K
b100100000 &
b100100000 P
1!
#740
0!
#745
b1001001 [
b100101000 @
b100101000 K
b100100100 &
b100100100 P
1!
#750
0!
#755
b1001010 [
b100101100 @
b100101100 K
b100101000 &
b100101000 P
1!
#760
0!
#765
b1001011 [
b100110000 @
b100110000 K
b100101100 &
b100101100 P
1!
#770
0!
#775
b1001100 [
b100110100 @
b100110100 K
b100110000 &
b100110000 P
1!
#780
0!
#785
b1001101 [
b100111000 @
b100111000 K
b100110100 &
b100110100 P
1!
#790
0!
#795
b1001110 [
b100111100 @
b100111100 K
b100111000 &
b100111000 P
1!
#800
0!
#805
b1001111 [
b101000000 @
b101000000 K
b100111100 &
b100111100 P
1!
#810
0!
#815
b1010000 [
b101000100 @
b101000100 K
b101000000 &
b101000000 P
1!
#820
0!
#825
b1010001 [
b101001000 @
b101001000 K
b101000100 &
b101000100 P
1!
#830
0!
#835
b1010010 [
b101001100 @
b101001100 K
b101001000 &
b101001000 P
1!
#840
0!
#845
b1010011 [
b101010000 @
b101010000 K
b101001100 &
b101001100 P
1!
#850
0!
#855
b1010100 [
b101010100 @
b101010100 K
b101010000 &
b101010000 P
1!
#860
0!
#865
b1010101 [
b101011000 @
b101011000 K
b101010100 &
b101010100 P
1!
#870
0!
#875
b1010110 [
b101011100 @
b101011100 K
b101011000 &
b101011000 P
1!
#880
0!
#885
b1010111 [
b101100000 @
b101100000 K
b101011100 &
b101011100 P
1!
#890
0!
#895
b1011000 [
b101100100 @
b101100100 K
b101100000 &
b101100000 P
1!
#900
0!
#905
b1011001 [
b101101000 @
b101101000 K
b101100100 &
b101100100 P
1!
#910
0!
#915
b1011010 [
b101101100 @
b101101100 K
b101101000 &
b101101000 P
1!
#920
0!
#925
b1011011 [
b101110000 @
b101110000 K
b101101100 &
b101101100 P
1!
#930
0!
#935
b1011100 [
b101110100 @
b101110100 K
b101110000 &
b101110000 P
1!
#940
0!
#945
b1011101 [
b101111000 @
b101111000 K
b101110100 &
b101110100 P
1!
#950
0!
#955
b1011110 [
b101111100 @
b101111100 K
b101111000 &
b101111000 P
1!
#960
0!
#965
b1011111 [
b110000000 @
b110000000 K
b101111100 &
b101111100 P
1!
#970
0!
#975
b1100000 [
b110000100 @
b110000100 K
b110000000 &
b110000000 P
1!
#980
0!
#985
b1100001 [
b110001000 @
b110001000 K
b110000100 &
b110000100 P
1!
#990
0!
#995
b1100010 [
b110001100 @
b110001100 K
b110001000 &
b110001000 P
1!
#1000
0!
#1005
b1100011 [
b110010000 @
b110010000 K
b110001100 &
b110001100 P
1!
#1010
0!
#1015
b1100100 [
b110010100 @
b110010100 K
b110010000 &
b110010000 P
1!
#1020
0!
#1025
b1100101 [
b110011000 @
b110011000 K
b110010100 &
b110010100 P
1!
#1030
0!
#1035
b1100110 [
b110011100 @
b110011100 K
b110011000 &
b110011000 P
1!
#1040
0!
#1045
b1100111 [
b110100000 @
b110100000 K
b110011100 &
b110011100 P
1!
#1050
0!
#1055
b1101000 [
b110100100 @
b110100100 K
b110100000 &
b110100000 P
1!
#1060
0!
#1065
b1101001 [
b110101000 @
b110101000 K
b110100100 &
b110100100 P
1!
#1070
0!
#1075
b1101010 [
b110101100 @
b110101100 K
b110101000 &
b110101000 P
1!
#1080
0!
#1085
b1101011 [
b110110000 @
b110110000 K
b110101100 &
b110101100 P
1!
#1090
0!
#1095
b1101100 [
b110110100 @
b110110100 K
b110110000 &
b110110000 P
1!
#1100
0!
#1105
b1101101 [
b110111000 @
b110111000 K
b110110100 &
b110110100 P
1!
#1110
0!
#1115
b1101110 [
b110111100 @
b110111100 K
b110111000 &
b110111000 P
1!
#1120
0!
#1125
b1101111 [
b111000000 @
b111000000 K
b110111100 &
b110111100 P
1!
#1130
0!
#1135
b1110000 [
b111000100 @
b111000100 K
b111000000 &
b111000000 P
1!
#1140
0!
#1145
b1110001 [
b111001000 @
b111001000 K
b111000100 &
b111000100 P
1!
#1150
0!
#1155
b1110010 [
b111001100 @
b111001100 K
b111001000 &
b111001000 P
1!
#1160
0!
#1165
b1110011 [
b111010000 @
b111010000 K
b111001100 &
b111001100 P
1!
#1170
0!
#1175
b1110100 [
b111010100 @
b111010100 K
b111010000 &
b111010000 P
1!
#1180
0!
#1185
b1110101 [
b111011000 @
b111011000 K
b111010100 &
b111010100 P
1!
#1190
0!
#1195
b1110110 [
b111011100 @
b111011100 K
b111011000 &
b111011000 P
1!
#1200
0!
#1205
b1110111 [
b111100000 @
b111100000 K
b111011100 &
b111011100 P
1!
#1210
0!
#1215
b1111000 [
b111100100 @
b111100100 K
b111100000 &
b111100000 P
1!
#1220
0!
#1225
b1111001 [
b111101000 @
b111101000 K
b111100100 &
b111100100 P
1!
#1230
0!
#1235
b1111010 [
b111101100 @
b111101100 K
b111101000 &
b111101000 P
1!
#1240
0!
#1245
b1111011 [
b111110000 @
b111110000 K
b111101100 &
b111101100 P
1!
#1250
0!
#1255
b1111100 [
b111110100 @
b111110100 K
b111110000 &
b111110000 P
1!
#1260
0!
#1265
b1111101 [
b111111000 @
b111111000 K
b111110100 &
b111110100 P
1!
#1270
0!
#1275
b1111110 [
b111111100 @
b111111100 K
b111111000 &
b111111000 P
1!
#1280
0!
#1285
b1111111 [
b1000000000 @
b1000000000 K
b111111100 &
b111111100 P
1!
#1290
0!
#1295
b10000000 [
b1000000100 @
b1000000100 K
b1000000000 &
b1000000000 P
1!
#1300
0!
#1305
b10000001 [
b1000001000 @
b1000001000 K
b1000000100 &
b1000000100 P
1!
#1310
0!
#1315
b10000010 [
b1000001100 @
b1000001100 K
b1000001000 &
b1000001000 P
1!
#1320
0!
#1325
b10000011 [
b1000010000 @
b1000010000 K
b1000001100 &
b1000001100 P
1!
#1330
0!
#1335
b10000100 [
b1000010100 @
b1000010100 K
b1000010000 &
b1000010000 P
1!
#1340
0!
#1345
b10000101 [
b1000011000 @
b1000011000 K
b1000010100 &
b1000010100 P
1!
#1350
0!
#1355
b10000110 [
b1000011100 @
b1000011100 K
b1000011000 &
b1000011000 P
1!
#1360
0!
#1365
b10000111 [
b1000100000 @
b1000100000 K
b1000011100 &
b1000011100 P
1!
#1370
0!
#1375
b10001000 [
b1000100100 @
b1000100100 K
b1000100000 &
b1000100000 P
1!
#1380
0!
#1385
b10001001 [
b1000101000 @
b1000101000 K
b1000100100 &
b1000100100 P
1!
#1390
0!
#1395
b10001010 [
b1000101100 @
b1000101100 K
b1000101000 &
b1000101000 P
1!
#1400
0!
#1405
b10001011 [
b1000110000 @
b1000110000 K
b1000101100 &
b1000101100 P
1!
#1410
0!
#1415
b10001100 [
b1000110100 @
b1000110100 K
b1000110000 &
b1000110000 P
1!
#1420
0!
#1425
b10001101 [
b1000111000 @
b1000111000 K
b1000110100 &
b1000110100 P
1!
#1430
0!
#1435
b10001110 [
b1000111100 @
b1000111100 K
b1000111000 &
b1000111000 P
1!
#1440
0!
#1445
b10001111 [
b1001000000 @
b1001000000 K
b1000111100 &
b1000111100 P
1!
#1450
0!
#1455
b10010000 [
b1001000100 @
b1001000100 K
b1001000000 &
b1001000000 P
1!
#1460
0!
#1465
b10010001 [
b1001001000 @
b1001001000 K
b1001000100 &
b1001000100 P
1!
#1470
0!
#1475
b10010010 [
b1001001100 @
b1001001100 K
b1001001000 &
b1001001000 P
1!
#1480
0!
#1485
b10010011 [
b1001010000 @
b1001010000 K
b1001001100 &
b1001001100 P
1!
#1490
0!
#1495
b10010100 [
b1001010100 @
b1001010100 K
b1001010000 &
b1001010000 P
1!
#1500
0!
#1505
b10010101 [
b1001011000 @
b1001011000 K
b1001010100 &
b1001010100 P
1!
#1510
0!
#1515
b10010110 [
b1001011100 @
b1001011100 K
b1001011000 &
b1001011000 P
1!
#1520
0!
